decoder.v
module BCD(clk,rst,Load,Q_seg,Din);
input clk;
input rst;
input Load;
input[3:0] Din;
output [3:0]  Q1;
reg [3:0] Q1;
output [7:0] Q_seg;
reg [7:0] Q_seg;

always@(posedge clk)
begin
  if(!rst)
    Q1 <= 4'b0000;
  else if(Load)
    Q1 <= Din;
  else if(Q1==9)
    Q1  <= 4'b0000;
  else
    Q1<=Q1+1;
  end
 always@(*) begin
   case(Q1)
     4'b0000: Q_seg = 8'b11000000;
     4'b0001: Q_seg = 8'b11111001;
     4'b0010: Q_seg = 8'b10100100;
     4'b0011: Q_seg = 8'b10110000;
     4'b0100: Q_seg = 8'b10011001;
     4'b0101: Q_seg = 8'b10010010;
     4'b0110: Q_seg = 8'b10000010;
     4'b0111: Q_seg = 8'b11111000;
     4'b1000: Q_seg = 8'b10000000;
     4'b1001: Q_seg = 8'b00100000;
     4'b1010: Q_seg = 8'b00000000;
   endcase
 end
endmodule

decoder_tb.v
module  decoder_tb();
reg clk;
reg rst;
reg Load;
reg [3:0] Din;
wire[3:0] Q1;
wire[7:0] Q_seg;

  parameter PERIOD  = 20;
  parameter real DUTY_CYCLE  = 0.5;
  parameter OFFSET  = 0;
  initial
  begin
      #OFFSET;
      forever
      begin
        clk = 1'b1;
        #(PERIOD-(PERIOD*DUTY_CYCLE))
        clk = 1'b0;
        #(PERIOD*DUTY_CYCLE);
        end
      end
    initial begin
          rst = 1'b0;
      Load = 1'b0;
      Din = 4;
      #5 rst = 1'b1;
      #350 Load = 1'b0;
      #20 Load = 1'b1;
      #10 Load  = 1'b0;
      #200 rst = 1'b0;
      #50 rst = 1'b1;
      #1000 $finish;
    end
    initial
    begin
          $dumpfile("decoder.vcd");
          $dumpvars(0,decoder_tb);
    end
    BCD decoder_tb( .clk(clk), .rst(rst), .Q_seg(Q_seg), .Din(Din), .Load(Load));
    endmodule

decoder.vcd
$date
	Wed May  4 23:53:50 2022
$end
$version
	Icarus Verilog
$end
$timescale
	1s
$end
$scope module decoder_tb $end
$scope module decoder_tb $end
$var wire 4 ! Din [3:0] $end
$var wire 1 " Load $end
$var wire 1 # clk $end
$var wire 1 $ rst $end
$var reg 4 % Q1 [3:0] $end
$var reg 8 & Q_seg [7:0] $end
$upscope $end
$upscope $end
$enddefinitions $end
#0
$dumpvars
b11000000 &
b0 %
0$
1#
0"
b100 !
$end
#5
1$
#10
0#
#20
b11111001 &
b1 %
1#
#30
0#
#40
b10100100 &
b10 %
1#
#50
0#
#60
b10110000 &
b11 %
1#
#70
0#
#80
b10011001 &
b100 %
1#
#90
0#
#100
b10010010 &
b101 %
1#
#110
0#
#120
b10000010 &
b110 %
1#
#130
0#
#140
b11111000 &
b111 %
1#
#150
0#
#160
b10000000 &
b1000 %
1#
#170
0#
#180
b100000 &
b1001 %
1#
#190
0#
#200
b11000000 &
b0 %
1#
#210
0#
#220
b11111001 &
b1 %
1#
#230
0#
#240
b10100100 &
b10 %
1#
#250
0#
#260
b10110000 &
b11 %
1#
#270
0#
#280
b10011001 &
b100 %
1#
#290
0#
#300
b10010010 &
b101 %
1#
#310
0#
#320
b10000010 &
b110 %
1#
#330
0#
#340
b11111000 &
b111 %
1#
#350
0#
#360
b10000000 &
b1000 %
1#
#370
0#
#375
1"
#380
b10011001 &
b100 %
1#
#385
0"
#390
0#
#400
b10010010 &
b101 %
1#
#410
0#
#420
b10000010 &
b110 %
1#
#430
0#
#440
b11111000 &
b111 %
1#
#450
0#
#460
b10000000 &
b1000 %
1#
#470
0#
#480
b100000 &
b1001 %
1#
#490
0#
#500
b11000000 &
b0 %
1#
#510
0#
#520
b11111001 &
b1 %
1#
#530
0#
#540
b10100100 &
b10 %
1#
#550
0#
#560
b10110000 &
b11 %
1#
#570
0#
#580
b10011001 &
b100 %
1#
#585
0$
#590
0#
#600
b11000000 &
b0 %
1#
#610
0#
#620
1#
#630
0#
#635
1$
#640
b11111001 &
b1 %
1#
#650
0#
#660
b10100100 &
b10 %
1#
#670
0#
#680
b10110000 &
b11 %
1#
#690
0#
#700
b10011001 &
b100 %
1#
#710
0#
#720
b10010010 &
b101 %
1#
#730
0#
#740
b10000010 &
b110 %
1#
#750
0#
#760
b11111000 &
b111 %
1#
#770
0#
#780
b10000000 &
b1000 %
1#
#790
0#
#800
b100000 &
b1001 %
1#
#810
0#
#820
b11000000 &
b0 %
1#
#830
0#
#840
b11111001 &
b1 %
1#
#850
0#
#860
b10100100 &
b10 %
1#
#870
0#
#880
b10110000 &
b11 %
1#
#890
0#
#900
b10011001 &
b100 %
1#
#910
0#
#920
b10010010 &
b101 %
1#
#930
0#
#940
b10000010 &
b110 %
1#
#950
0#
#960
b11111000 &
b111 %
1#
#970
0#
#980
b10000000 &
b1000 %
1#
#990
0#
#1000
b100000 &
b1001 %
1#
#1010
0#
#1020
b11000000 &
b0 %
1#
#1030
0#
#1040
b11111001 &
b1 %
1#
#1050
0#
#1060
b10100100 &
b10 %
1#
#1070
0#
#1080
b10110000 &
b11 %
1#
#1090
0#
#1100
b10011001 &
b100 %
1#
#1110
0#
#1120
b10010010 &
b101 %
1#
#1130
0#
#1140
b10000010 &
b110 %
1#
#1150
0#
#1160
b11111000 &
b111 %
1#
#1170
0#
#1180
b10000000 &
b1000 %
1#
#1190
0#
#1200
b100000 &
b1001 %
1#
#1210
0#
#1220
b11000000 &
b0 %
1#
#1230
0#
#1240
b11111001 &
b1 %
1#
#1250
0#
#1260
b10100100 &
b10 %
1#
#1270
0#
#1280
b10110000 &
b11 %
1#
#1290
0#
#1300
b10011001 &
b100 %
1#
#1310
0#
#1320
b10010010 &
b101 %
1#
#1330
0#
#1340
b10000010 &
b110 %
1#
#1350
0#
#1360
b11111000 &
b111 %
1#
#1370
0#
#1380
b10000000 &
b1000 %
1#
#1390
0#
#1400
b100000 &
b1001 %
1#
#1410
0#
#1420
b11000000 &
b0 %
1#
#1430
0#
#1440
b11111001 &
b1 %
1#
#1450
0#
#1460
b10100100 &
b10 %
1#
#1470
0#
#1480
b10110000 &
b11 %
1#
#1490
0#
#1500
b10011001 &
b100 %
1#
#1510
0#
#1520
b10010010 &
b101 %
1#
#1530
0#
#1540
b10000010 &
b110 %
1#
#1550
0#
#1560
b11111000 &
b111 %
1#
#1570
0#
#1580
b10000000 &
b1000 %
1#
#1590
0#
#1600
b100000 &
b1001 %
1#
#1610
0#
#1620
b11000000 &
b0 %
1#
